rearfloor/__init__.py
rearfloor/background_decorator.py
rearfloor-1.0.0.dist-info/LICENSE
rearfloor-1.0.0.dist-info/METADATA
rearfloor-1.0.0.dist-info/WHEEL
rearfloor-1.0.0.dist-info/top_level.txt
rearfloor-1.0.0.dist-info/RECORD
