Metadata-Version: 2.1
Name: rearfloor
Version: 1.0.0
Summary: Easily background your functions in just 10 characters
Home-page: https://github.com/breadbored/rearfloor
Author: Jason Carpenter
Author-email: brad@identex.co
License: UNKNOWN
Project-URL: Bug Tracker, https://github.com/breadbored/rearfloor/issues
Platform: UNKNOWN
Classifier: Programming Language :: Python :: 3
Classifier: License :: OSI Approved :: MIT License
Classifier: Operating System :: OS Independent
Requires-Python: >=3.3
License-File: LICENSE
Requires-Dist: asyncio ; python_version < "3.4"
